genrm/__init__.py
genrm/foo.py
genrm-0.0.1.dist-info/METADATA
genrm-0.0.1.dist-info/WHEEL
genrm-0.0.1.dist-info/licenses/LICENSE
genrm-0.0.1.dist-info/RECORD
