Metadata-Version: 2.4
Name: genrm
Version: 0.0.1
Summary: Generative Reward Models
Project-URL: Homepage, https://nlile.github.io/genrm/
Project-URL: Repository, https://github.com/nlile/genrm
Project-URL: Documentation, https://nlile.github.io/genrm/
Author-email: nlile <nathan@synthlabs.ai>
License-File: LICENSE
Keywords: python
Classifier: Intended Audience :: Developers
Classifier: Programming Language :: Python
Classifier: Programming Language :: Python :: 3
Classifier: Programming Language :: Python :: 3.9
Classifier: Programming Language :: Python :: 3.10
Classifier: Programming Language :: Python :: 3.11
Classifier: Programming Language :: Python :: 3.12
Classifier: Programming Language :: Python :: 3.13
Classifier: Topic :: Software Development :: Libraries :: Python Modules
Requires-Python: <4.0,>=3.9
